{
  "legislative_session": "2025-2026",
  "identifier": "S 571",
  "title": "Judge Donald Simons, retirement",
  "from_organization": "~{\"classification\": \"upper\"}",
  "classification": [
    "resolution"
  ],
  "subject": [],
  "abstracts": [
    {
      "note": "description",
      "abstract": "A SENATE RESOLUTION TO RECOGNIZE AND COMMEND THE HONORABLE DONALD JEFFREY SIMONS, MAGISTRATE JUDGE FOR RICHLAND COUNTY, UPON THE OCCASION OF HIS RETIREMENT FROM THE BENCH AND TO WISH HIM CONTINUED SUCCESS AND HAPPINESS IN ALL HIS FUTURE ENDEAVORS."
    }
  ],
  "other_titles": [],
  "other_identifiers": [],
  "actions": [
    {
      "description": "Introduced and adopted",
      "date": "2025-04-16",
      "organization_id": "~{\"classification\": \"upper\"}",
      "classification": [
        "introduction",
        "passage"
      ],
      "related_entities": []
    }
  ],
  "sponsorships": [
    {
      "name": "Jackson",
      "classification": "primary",
      "entity_type": "person",
      "primary": true,
      "person_id": "~{\"chamber\": \"upper\", \"name\": \"Jackson\"}",
      "organization_id": null
    }
  ],
  "related_bills": [],
  "versions": [
    {
      "note": "04/16/2025",
      "links": [
        {
          "url": "https://www.scstatehouse.gov/sess126_2025-2026/prever/571_20250416.htm",
          "media_type": "text/html"
        }
      ],
      "date": "",
      "classification": ""
    },
    {
      "note": "Filed",
      "links": [
        {
          "url": "https://www.scstatehouse.gov/sess126_2025-2026/bills/571.htm",
          "media_type": "text/html"
        },
        {
          "url": "https://www.scstatehouse.gov/sess126_2025-2026/bills/571.docx",
          "media_type": "application/vnd.openxmlformats-officedocument.wordprocessingml.document"
        }
      ],
      "date": "",
      "classification": ""
    }
  ],
  "documents": [],
  "citations": [],
  "sources": [
    {
      "url": "https://www.scstatehouse.gov/billsearch.php?billnumbers=571&session=126&summary=B",
      "note": ""
    }
  ],
  "extras": {},
  "jurisdiction": {
    "id": "ocd-jurisdiction/country:us/state:sc/government",
    "name": "South Carolina",
    "classification": "state",
    "division_id": "ocd-division/country:us/state:sc"
  },
  "scraped_at": "2025-07-28T18:25:38+00:00",
  "_id": "4271ab08-6be0-11f0-bf34-96e81bacb000"
}