{"legislative_session": "2025-2026", "identifier": "H 3950", "title": "Soil classifers", "from_organization": "~{\"classification\": \"lower\"}", "classification": ["bill"], "subject": [], "abstracts": [{"note": "description", "abstract": "A BILL TO AMEND THE SOUTH CAROLINA CODE OF LAWS BY AMENDING SECTION 40-65-40, RELATING TO PERSONS EXEMPT FROM LICENSURE AS PROFESSIONAL SOIL CLASSIFIERS, SO AS TO EXEMPT LICENSED PROFESSIONAL ENGINEERS PERFORMING SOIL EVALUATIONS IN CONNECTION WITH CONVENTIONAL ONSITE WASTEWATER SYSTEMS, AND TO PROVIDE THESE ENGINEERS MUST HAVE CERTAIN TRAINING, BONDING, AND INSURANCE."}], "other_titles": [], "other_identifiers": [], "actions": [{"description": "Introduced and read first time", "date": "2025-02-11", "organization_id": "~{\"classification\": \"lower\"}", "classification": ["introduction", "reading-1"], "related_entities": []}, {"description": "Referred to Committee on Agriculture, Natural Resources and Environmental Affairs", "date": "2025-02-11", "organization_id": "~{\"classification\": \"lower\"}", "classification": ["referral-committee"], "related_entities": []}, {"description": "Member(s) request name added as sponsor: Forrest", "date": "2025-03-10", "organization_id": "~{\"classification\": \"lower\"}", "classification": [], "related_entities": []}, {"description": "Committee report: Favorable with amendment Agriculture, Natural Resources and Environmental Affairs", "date": "2025-04-29", "organization_id": "~{\"classification\": \"lower\"}", "classification": ["committee-passage-favorable"], "related_entities": []}, {"description": "Amended", "date": "2025-04-30", "organization_id": "~{\"classification\": \"lower\"}", "classification": ["amendment-passage"], "related_entities": []}, {"description": "Read second time", "date": "2025-04-30", "organization_id": "~{\"classification\": \"lower\"}", "classification": ["reading-2"], "related_entities": []}, {"description": "Roll call Yeas-100  Nays-0", "date": "2025-04-30", "organization_id": "~{\"classification\": \"lower\"}", "classification": [], "related_entities": []}, {"description": "Read third time and sent to Senate", "date": "2025-05-01", "organization_id": "~{\"classification\": \"lower\"}", "classification": ["passage", "reading-3"], "related_entities": []}, {"description": "Introduced and read first time", "date": "2025-05-01", "organization_id": "~{\"classification\": \"upper\"}", "classification": ["introduction", "reading-1"], "related_entities": []}, {"description": "Referred to Committee on Labor, Commerce and Industry", "date": "2025-05-01", "organization_id": "~{\"classification\": \"upper\"}", "classification": ["referral-committee"], "related_entities": []}], "sponsorships": [{"name": "Hixon", "classification": "primary", "entity_type": "person", "primary": true, "person_id": "~{\"chamber\": \"lower\", \"name\": \"Hixon\"}", "organization_id": null}, {"name": "Forrest", "classification": "primary", "entity_type": "person", "primary": true, "person_id": "~{\"chamber\": \"lower\", \"name\": \"Forrest\"}", "organization_id": null}], "related_bills": [], "versions": [{"note": "02/11/2025", "links": [{"url": "https://www.scstatehouse.gov/sess126_2025-2026/prever/3950_20250211.htm", "media_type": "text/html"}], "date": "", "classification": ""}, {"note": "04/29/2025", "links": [{"url": "https://www.scstatehouse.gov/sess126_2025-2026/prever/3950_20250429.htm", "media_type": "text/html"}], "date": "", "classification": ""}, {"note": "04/30/2025", "links": [{"url": "https://www.scstatehouse.gov/sess126_2025-2026/prever/3950_20250430.htm", "media_type": "text/html"}], "date": "", "classification": ""}, {"note": "Filed", "links": [{"url": "https://www.scstatehouse.gov/sess126_2025-2026/bills/3950.htm", "media_type": "text/html"}, {"url": "https://www.scstatehouse.gov/sess126_2025-2026/bills/3950.docx", "media_type": "application/vnd.openxmlformats-officedocument.wordprocessingml.document"}], "date": "", "classification": ""}], "documents": [], "citations": [], "sources": [{"url": "https://www.scstatehouse.gov/billsearch.php?billnumbers=3950&session=126&summary=B", "note": ""}], "extras": {}, "jurisdiction": {"id": "ocd-jurisdiction/country:us/state:sc/government", "name": "South Carolina", "classification": "state", "division_id": "ocd-division/country:us/state:sc"}, "scraped_at": "2025-07-28T19:09:54+00:00", "_id": "71c56a6a-6be6-11f0-a8ef-5a1d9bfa3395"}