{"legislative_session": "2025-2026", "identifier": "S 336", "title": "Judicial Elections", "from_organization": "~{\"classification\": \"upper\"}", "classification": ["bill"], "subject": [], "abstracts": [{"note": "description", "abstract": "A BILL TO AMEND THE SOUTH CAROLINA CODE OF LAWS BY AMENDING SECTION 2-19-90, RELATING TO APPROVAL OF THE GENERAL ASSEMBLY IN JOINT SESSION, SO AS TO SET THE FIRST WEDNESDAY OF MARCH FOR THE ELECTIONS OF JUDGES BY THE GENERAL ASSEMBLY."}], "other_titles": [], "other_identifiers": [], "actions": [{"description": "Introduced and read first time", "date": "2025-02-12", "organization_id": "~{\"classification\": \"upper\"}", "classification": ["introduction", "reading-1"], "related_entities": []}, {"description": "Referred to Committee on Judiciary", "date": "2025-02-12", "organization_id": "~{\"classification\": \"upper\"}", "classification": ["referral-committee"], "related_entities": []}, {"description": "Referred to Subcommittee: Elliott (ch), Cash, Tedder, Devine, Fernandez, Kennedy, Walker", "date": "2025-02-27", "organization_id": "~{\"classification\": \"upper\"}", "classification": [], "related_entities": []}, {"description": "Committee report: Favorable Judiciary", "date": "2025-03-12", "organization_id": "~{\"classification\": \"upper\"}", "classification": ["committee-passage-favorable"], "related_entities": []}, {"description": "Amended", "date": "2025-03-20", "organization_id": "~{\"classification\": \"upper\"}", "classification": ["amendment-passage"], "related_entities": []}, {"description": "Read second time", "date": "2025-03-20", "organization_id": "~{\"classification\": \"upper\"}", "classification": ["reading-2"], "related_entities": []}, {"description": "Roll call Ayes-40  Nays-0", "date": "2025-03-20", "organization_id": "~{\"classification\": \"upper\"}", "classification": [], "related_entities": []}, {"description": "Read third time and sent to House", "date": "2025-03-25", "organization_id": "~{\"classification\": \"upper\"}", "classification": ["passage", "reading-3"], "related_entities": []}, {"description": "Introduced and read first time", "date": "2025-03-27", "organization_id": "~{\"classification\": \"lower\"}", "classification": ["introduction", "reading-1"], "related_entities": []}, {"description": "Referred to Committee on Judiciary", "date": "2025-03-27", "organization_id": "~{\"classification\": \"lower\"}", "classification": ["referral-committee"], "related_entities": []}], "sponsorships": [{"name": "Alexander", "classification": "primary", "entity_type": "person", "primary": true, "person_id": "~{\"chamber\": \"upper\", \"name\": \"Alexander\"}", "organization_id": null}, {"name": "Massey", "classification": "primary", "entity_type": "person", "primary": true, "person_id": "~{\"chamber\": \"upper\", \"name\": \"Massey\"}", "organization_id": null}, {"name": "Rankin", "classification": "primary", "entity_type": "person", "primary": true, "person_id": "~{\"chamber\": \"upper\", \"name\": \"Rankin\"}", "organization_id": null}], "related_bills": [], "versions": [{"note": "02/12/2025", "links": [{"url": "https://www.scstatehouse.gov/sess126_2025-2026/prever/336_20250212.htm", "media_type": "text/html"}], "date": "", "classification": ""}, {"note": "03/12/2025", "links": [{"url": "https://www.scstatehouse.gov/sess126_2025-2026/prever/336_20250312.htm", "media_type": "text/html"}], "date": "", "classification": ""}, {"note": "03/20/2025", "links": [{"url": "https://www.scstatehouse.gov/sess126_2025-2026/prever/336_20250320.htm", "media_type": "text/html"}], "date": "", "classification": ""}, {"note": "Filed", "links": [{"url": "https://www.scstatehouse.gov/sess126_2025-2026/bills/336.htm", "media_type": "text/html"}, {"url": "https://www.scstatehouse.gov/sess126_2025-2026/bills/336.docx", "media_type": "application/vnd.openxmlformats-officedocument.wordprocessingml.document"}], "date": "", "classification": ""}], "documents": [], "citations": [], "sources": [{"url": "https://www.scstatehouse.gov/billsearch.php?billnumbers=336&session=126&summary=B", "note": ""}], "extras": {}, "jurisdiction": {"id": "ocd-jurisdiction/country:us/state:sc/government", "name": "South Carolina", "classification": "state", "division_id": "ocd-division/country:us/state:sc"}, "scraped_at": "2025-07-28T18:27:06+00:00", "_id": "77176d66-6be0-11f0-bf34-96e81bacb000"}