{"legislative_session": "2025-2026", "identifier": "H 3149", "title": "Motor vehicle offenses decriminalized", "from_organization": "~{\"classification\": \"lower\"}", "classification": ["bill"], "subject": [], "abstracts": [{"note": "description", "abstract": "A BILL TO AMEND THE SOUTH CAROLINA CODE OF LAWS BY AMENDING SECTION 56-5-1520, RELATING TO MAXIMUM SPEED LIMITS, SO AS TO REVISE THE PENALTIES FOR VIOLATIONS; BY AMENDING SECTION 56-5-5015, RELATING TO THE OPERATION OF MOTOR VEHICLES EQUIPPED WITH SUNSCREEN DEVICES, SO AS TO REVISE THE PENALTIES FOR VIOLATIONS; BY AMENDING SECTION 56-5-6190, RELATING TO THE CLASSIFICATION OF CERTAIN CRIMES AS MISDEMEANORS AND FELONIES, SO AS TO PROVIDE PERSONS CONVICTED OF VIOLATIONS OF PROVISIONS FOR WHICH OTHER PENALTIES ARE NOT PROVIDED SHALL BE FINED NOT MORE THAN ONE HUNDRED DOLLARS; AND BY REPEALING SECTION 56-5-730 RELATING TO THE CLASSIFICATION OF CERTAIN OFFENSES AS MISDEMEANORS UNLESS OTHERWISE DECLARED."}], "other_titles": [], "other_identifiers": [], "actions": [{"description": "Prefiled", "date": "2024-12-05", "organization_id": "~{\"classification\": \"lower\"}", "classification": ["filing"], "related_entities": []}, {"description": "Referred to Committee on Judiciary", "date": "2024-12-05", "organization_id": "~{\"classification\": \"lower\"}", "classification": ["referral-committee"], "related_entities": []}, {"description": "Introduced and read first time", "date": "2025-01-14", "organization_id": "~{\"classification\": \"lower\"}", "classification": ["introduction", "reading-1"], "related_entities": []}, {"description": "Referred to Committee on Judiciary", "date": "2025-01-14", "organization_id": "~{\"classification\": \"lower\"}", "classification": ["referral-committee"], "related_entities": []}], "sponsorships": [{"name": "Rutherford", "classification": "primary", "entity_type": "person", "primary": true, "person_id": "~{\"chamber\": \"lower\", \"name\": \"Rutherford\"}", "organization_id": null}], "related_bills": [], "versions": [{"note": "12/05/2024", "links": [{"url": "https://www.scstatehouse.gov/sess126_2025-2026/prever/3149_20241205.htm", "media_type": "text/html"}], "date": "", "classification": ""}, {"note": "Filed", "links": [{"url": "https://www.scstatehouse.gov/sess126_2025-2026/bills/3149.htm", "media_type": "text/html"}, {"url": "https://www.scstatehouse.gov/sess126_2025-2026/bills/3149.docx", "media_type": "application/vnd.openxmlformats-officedocument.wordprocessingml.document"}], "date": "", "classification": ""}], "documents": [], "citations": [], "sources": [{"url": "https://www.scstatehouse.gov/billsearch.php?billnumbers=3149&session=126&summary=B", "note": ""}], "extras": {}, "jurisdiction": {"id": "ocd-jurisdiction/country:us/state:sc/government", "name": "South Carolina", "classification": "state", "division_id": "ocd-division/country:us/state:sc"}, "scraped_at": "2025-07-28T18:36:43+00:00", "_id": "cf3fb3f8-6be1-11f0-bf34-96e81bacb000"}