{"legislative_session": "2025-2026", "identifier": "S 421", "title": "Participation in school activities and programs", "from_organization": "~{\"classification\": \"upper\"}", "classification": ["bill"], "subject": [], "abstracts": [{"note": "description", "abstract": "A BILL TO AMEND THE SOUTH CAROLINA CODE OF LAWS BY AMENDING SECTION 59-63-100, RELATING TO PARTICIPATION IN INTERSCHOLASTIC ACTIVITIES OF PUBLIC SCHOOL DISTRICTS BY HOME SCHOOL, CHARTER SCHOOL, AND GOVERNOR'S SCHOOL STUDENTS, SO AS TO INCLUDE PARTICIPATION IN COCURRICULAR ACTIVITIES, EXTRACURRICULAR ACTIVITIES, AND CAREER AND TECHNICAL EDUCATION, AND TO PROVIDE EQUAL TREATMENT FOR SUCH STUDENTS AND STUDENTS ENROLLED IN PUBLIC SCHOOLS IN THE DISTRICT, AND TO DEFINE \"CAREER AND TECHNICAL EDUCATION,\" \"COCURRICULAR ACTIVITIES,\" AND \"EXTRACURRICULAR ACTIVITIES,\" AMONG OTHER THINGS."}], "other_titles": [], "other_identifiers": [], "actions": [{"description": "Introduced and read first time", "date": "2025-03-05", "organization_id": "~{\"classification\": \"upper\"}", "classification": ["introduction", "reading-1"], "related_entities": []}, {"description": "Referred to Committee on Education", "date": "2025-03-05", "organization_id": "~{\"classification\": \"upper\"}", "classification": ["referral-committee"], "related_entities": []}, {"description": "Scrivener's error corrected", "date": "2025-03-06", "organization_id": "~{\"classification\": \"legislature\"}", "classification": [], "related_entities": []}], "sponsorships": [{"name": "Grooms", "classification": "primary", "entity_type": "person", "primary": true, "person_id": "~{\"chamber\": \"upper\", \"name\": \"Grooms\"}", "organization_id": null}, {"name": "Zell", "classification": "primary", "entity_type": "person", "primary": true, "person_id": "~{\"chamber\": \"upper\", \"name\": \"Zell\"}", "organization_id": null}], "related_bills": [], "versions": [{"note": "03/05/2025", "links": [{"url": "https://www.scstatehouse.gov/sess126_2025-2026/prever/421_20250305.htm", "media_type": "text/html"}], "date": "", "classification": ""}, {"note": "03/06/2025", "links": [{"url": "https://www.scstatehouse.gov/sess126_2025-2026/prever/421_20250306.htm", "media_type": "text/html"}], "date": "", "classification": ""}, {"note": "Filed", "links": [{"url": "https://www.scstatehouse.gov/sess126_2025-2026/bills/421.htm", "media_type": "text/html"}, {"url": "https://www.scstatehouse.gov/sess126_2025-2026/bills/421.docx", "media_type": "application/vnd.openxmlformats-officedocument.wordprocessingml.document"}], "date": "", "classification": ""}], "documents": [], "citations": [], "sources": [{"url": "https://www.scstatehouse.gov/billsearch.php?billnumbers=421&session=126&summary=B", "note": ""}], "extras": {}, "jurisdiction": {"id": "ocd-jurisdiction/country:us/state:sc/government", "name": "South Carolina", "classification": "state", "division_id": "ocd-division/country:us/state:sc"}, "scraped_at": "2025-07-28T18:26:33+00:00", "_id": "63a82a36-6be0-11f0-bf34-96e81bacb000"}