{"legislative_session": "2025-2026", "identifier": "S 136", "title": "Dismissal of pending gun possession charges", "from_organization": "~{\"classification\": \"upper\"}", "classification": ["bill"], "subject": [], "abstracts": [{"note": "description", "abstract": "AN ACT TO AMEND THE SOUTH CAROLINA CODE OF LAWS BY AMENDING SECTION 17-1-65, RELATING TO THE EXPUNGEMENT OF CONVICTIONS FOR THE UNLAWFUL POSSESSION OF HANDGUNS, SO AS TO PROVIDE THE STATE MUST DISMISS AND EXPUNGE CERTAIN PENDING UNLAWFUL HANDGUN POSSESSION CHARGES THAT OCCURRED PRIOR TO THE ENACTMENT OF THE SOUTH CAROLINA CONSTITUTIONAL CARRY/SECOND AMENDMENT PRESERVATION ACT OF 2024, AND TO PROVIDE THE DISMISSAL OF THESE CHARGES MAY NOT SERVE AS A BASIS OR SUPPORT FOR CIVIL ACTIONS DUE TO THE ARREST. - RATIFIED TITLE"}], "other_titles": [], "other_identifiers": [], "actions": [{"description": "Prefiled", "date": "2024-12-11", "organization_id": "~{\"classification\": \"upper\"}", "classification": ["filing"], "related_entities": []}, {"description": "Referred to Committee on Judiciary", "date": "2024-12-11", "organization_id": "~{\"classification\": \"upper\"}", "classification": ["referral-committee"], "related_entities": []}, {"description": "Introduced and read first time", "date": "2025-01-14", "organization_id": "~{\"classification\": \"upper\"}", "classification": ["introduction", "reading-1"], "related_entities": []}, {"description": "Referred to Committee on Judiciary", "date": "2025-01-14", "organization_id": "~{\"classification\": \"upper\"}", "classification": ["referral-committee"], "related_entities": []}, {"description": "Scrivener's error corrected", "date": "2025-01-17", "organization_id": "~{\"classification\": \"legislature\"}", "classification": [], "related_entities": []}, {"description": "Committee report: Favorable Judiciary", "date": "2025-02-19", "organization_id": "~{\"classification\": \"upper\"}", "classification": ["committee-passage-favorable"], "related_entities": []}, {"description": "Amended", "date": "2025-02-25", "organization_id": "~{\"classification\": \"upper\"}", "classification": ["amendment-passage"], "related_entities": []}, {"description": "Read second time", "date": "2025-02-25", "organization_id": "~{\"classification\": \"upper\"}", "classification": ["reading-2"], "related_entities": []}, {"description": "Roll call Ayes-43  Nays-0", "date": "2025-02-25", "organization_id": "~{\"classification\": \"upper\"}", "classification": [], "related_entities": []}, {"description": "Read third time and sent to House", "date": "2025-02-26", "organization_id": "~{\"classification\": \"upper\"}", "classification": ["passage", "reading-3"], "related_entities": []}, {"description": "Introduced and read first time", "date": "2025-03-04", "organization_id": "~{\"classification\": \"lower\"}", "classification": ["introduction", "reading-1"], "related_entities": []}, {"description": "Referred to Committee on Judiciary", "date": "2025-03-04", "organization_id": "~{\"classification\": \"lower\"}", "classification": ["referral-committee"], "related_entities": []}, {"description": "Committee report: Favorable with amendment Judiciary", "date": "2025-04-30", "organization_id": "~{\"classification\": \"lower\"}", "classification": ["committee-passage-favorable"], "related_entities": []}, {"description": "Amended", "date": "2025-05-01", "organization_id": "~{\"classification\": \"lower\"}", "classification": ["amendment-passage"], "related_entities": []}, {"description": "Read second time", "date": "2025-05-01", "organization_id": "~{\"classification\": \"lower\"}", "classification": ["reading-2"], "related_entities": []}, {"description": "Roll call Yeas-107  Nays-5", "date": "2025-05-01", "organization_id": "~{\"classification\": \"lower\"}", "classification": [], "related_entities": []}, {"description": "Unanimous consent for third reading on next legislative day", "date": "2025-05-01", "organization_id": "~{\"classification\": \"lower\"}", "classification": [], "related_entities": []}, {"description": "Scrivener's error corrected", "date": "2025-05-05", "organization_id": "~{\"classification\": \"legislature\"}", "classification": [], "related_entities": []}, {"description": "Read third time and returned to Senate with amendments", "date": "2025-05-02", "organization_id": "~{\"classification\": \"lower\"}", "classification": ["passage", "reading-3"], "related_entities": []}, {"description": "House amendment amended", "date": "2025-05-06", "organization_id": "~{\"classification\": \"upper\"}", "classification": ["amendment-amendment"], "related_entities": []}, {"description": "Roll call Ayes-45  Nays-0", "date": "2025-05-06", "organization_id": "~{\"classification\": \"upper\"}", "classification": [], "related_entities": []}, {"description": "Returned to House with amendments", "date": "2025-05-06", "organization_id": "~{\"classification\": \"upper\"}", "classification": [], "related_entities": []}, {"description": "Scrivener's error corrected", "date": "2025-05-07", "organization_id": "~{\"classification\": \"legislature\"}", "classification": [], "related_entities": []}, {"description": "Concurred in Senate amendment and enrolled", "date": "2025-05-08", "organization_id": "~{\"classification\": \"lower\"}", "classification": [], "related_entities": []}, {"description": "Roll call Yeas-109  Nays-0", "date": "2025-05-08", "organization_id": "~{\"classification\": \"lower\"}", "classification": [], "related_entities": []}, {"description": "Ratified R 86", "date": "2025-05-20", "organization_id": "~{\"classification\": \"legislature\"}", "classification": [], "related_entities": []}, {"description": "Vetoed by Governor", "date": "2025-05-22", "organization_id": "~{\"classification\": \"legislature\"}", "classification": ["executive-veto"], "related_entities": []}, {"description": "Veto overridden Ayes-44  Nays-0", "date": "2025-05-28", "organization_id": "~{\"classification\": \"upper\"}", "classification": ["veto-override-passage"], "related_entities": []}], "sponsorships": [{"name": "Tedder", "classification": "primary", "entity_type": "person", "primary": true, "person_id": "~{\"chamber\": \"upper\", \"name\": \"Tedder\"}", "organization_id": null}, {"name": "Leber", "classification": "primary", "entity_type": "person", "primary": true, "person_id": "~{\"chamber\": \"upper\", \"name\": \"Leber\"}", "organization_id": null}, {"name": "Kimbrell", "classification": "primary", "entity_type": "person", "primary": true, "person_id": "~{\"chamber\": \"upper\", \"name\": \"Kimbrell\"}", "organization_id": null}, {"name": "Rice", "classification": "primary", "entity_type": "person", "primary": true, "person_id": "~{\"chamber\": \"upper\", \"name\": \"Rice\"}", "organization_id": null}], "related_bills": [], "versions": [{"note": "12/11/2024", "links": [{"url": "https://www.scstatehouse.gov/sess126_2025-2026/prever/136_20241211.htm", "media_type": "text/html"}], "date": "", "classification": ""}, {"note": "1/17/2025", "links": [{"url": "https://www.scstatehouse.gov/sess126_2025-2026/prever/136_20250117.htm", "media_type": "text/html"}], "date": "", "classification": ""}, {"note": "2/19/2025", "links": [{"url": "https://www.scstatehouse.gov/sess126_2025-2026/prever/136_20250219.htm", "media_type": "text/html"}], "date": "", "classification": ""}, {"note": "2/25/2025", "links": [{"url": "https://www.scstatehouse.gov/sess126_2025-2026/prever/136_20250225.htm", "media_type": "text/html"}], "date": "", "classification": ""}, {"note": "4/30/2025", "links": [{"url": "https://www.scstatehouse.gov/sess126_2025-2026/prever/136_20250430.htm", "media_type": "text/html"}], "date": "", "classification": ""}, {"note": "5/1/2025", "links": [{"url": "https://www.scstatehouse.gov/sess126_2025-2026/prever/136_20250501.htm", "media_type": "text/html"}], "date": "", "classification": ""}, {"note": "5/5/2025", "links": [{"url": "https://www.scstatehouse.gov/sess126_2025-2026/prever/136_20250505.htm", "media_type": "text/html"}], "date": "", "classification": ""}, {"note": "5/6/2025", "links": [{"url": "https://www.scstatehouse.gov/sess126_2025-2026/prever/136_20250506.htm", "media_type": "text/html"}], "date": "", "classification": ""}, {"note": "5/7/2025", "links": [{"url": "https://www.scstatehouse.gov/sess126_2025-2026/prever/136_20250507.htm", "media_type": "text/html"}], "date": "", "classification": ""}, {"note": "Filed", "links": [{"url": "https://www.scstatehouse.gov/sess126_2025-2026/bills/136.htm", "media_type": "text/html"}, {"url": "https://www.scstatehouse.gov/sess126_2025-2026/bills/136.docx", "media_type": "application/vnd.openxmlformats-officedocument.wordprocessingml.document"}], "date": "", "classification": ""}], "documents": [], "citations": [], "sources": [{"url": "https://www.scstatehouse.gov/billsearch.php?billnumbers=136&session=126&summary=B", "note": ""}], "extras": {}, "jurisdiction": {"id": "ocd-jurisdiction/country:us/state:sc/government", "name": "South Carolina", "classification": "state", "division_id": "ocd-division/country:us/state:sc"}, "scraped_at": "2025-07-28T19:09:35+00:00", "_id": "66bdc144-6be6-11f0-a8ef-5a1d9bfa3395"}