{"legislative_session": "2025-2026", "identifier": "H 3082", "title": "Family Court", "from_organization": "~{\"classification\": \"lower\"}", "classification": ["bill"], "subject": [], "abstracts": [{"note": "description", "abstract": "A BILL TO AMEND THE SOUTH CAROLINA CODE OF LAWS BY ADDING SECTION 63-3-635 SO AS TO AUTHORIZE DISCOVERY AS A MATTER OF RIGHT IN CERTAIN FAMILY COURT CASES."}], "other_titles": [], "other_identifiers": [], "actions": [{"description": "Prefiled", "date": "2024-12-05", "organization_id": "~{\"classification\": \"lower\"}", "classification": ["filing"], "related_entities": []}, {"description": "Referred to Committee on Judiciary", "date": "2024-12-05", "organization_id": "~{\"classification\": \"lower\"}", "classification": ["referral-committee"], "related_entities": []}, {"description": "Introduced and read first time", "date": "2025-01-14", "organization_id": "~{\"classification\": \"lower\"}", "classification": ["introduction", "reading-1"], "related_entities": []}, {"description": "Referred to Committee on Judiciary", "date": "2025-01-14", "organization_id": "~{\"classification\": \"lower\"}", "classification": ["referral-committee"], "related_entities": []}], "sponsorships": [{"name": "Gatch", "classification": "primary", "entity_type": "person", "primary": true, "person_id": "~{\"chamber\": \"lower\", \"name\": \"Gatch\"}", "organization_id": null}], "related_bills": [], "versions": [{"note": "12/05/2024", "links": [{"url": "https://www.scstatehouse.gov/sess126_2025-2026/prever/3082_20241205.htm", "media_type": "text/html"}], "date": "", "classification": ""}, {"note": "Filed", "links": [{"url": "https://www.scstatehouse.gov/sess126_2025-2026/bills/3082.htm", "media_type": "text/html"}, {"url": "https://www.scstatehouse.gov/sess126_2025-2026/bills/3082.docx", "media_type": "application/vnd.openxmlformats-officedocument.wordprocessingml.document"}], "date": "", "classification": ""}], "documents": [], "citations": [], "sources": [{"url": "https://www.scstatehouse.gov/billsearch.php?billnumbers=3082&session=126&summary=B", "note": ""}], "extras": {}, "jurisdiction": {"id": "ocd-jurisdiction/country:us/state:sc/government", "name": "South Carolina", "classification": "state", "division_id": "ocd-division/country:us/state:sc"}, "scraped_at": "2025-07-28T18:36:21+00:00", "_id": "c1d485cc-6be1-11f0-bf34-96e81bacb000"}