{
  "legislative_session": "2025-2026",
  "identifier": "S 643",
  "title": "Heather Harris, Board of Pharmacy",
  "from_organization": "~{\"classification\": \"upper\"}",
  "classification": [
    "resolution"
  ],
  "subject": [],
  "abstracts": [
    {
      "note": "description",
      "abstract": "A SENATE RESOLUTION TO RECOGNIZE HEATHER HARRIS FOR HER SERVICE TO THE SOUTH CAROLINA BOARD OF PHARMACY, TO COMMEND HER FOR HER MANY YEARS OF DEDICATED SERVICE, AND TO WISH HER MUCH HAPPINESS AND FULFILLMENT IN THE YEARS AHEAD."
    }
  ],
  "other_titles": [],
  "other_identifiers": [],
  "actions": [
    {
      "description": "Introduced and adopted",
      "date": "2025-05-06",
      "organization_id": "~{\"classification\": \"upper\"}",
      "classification": [
        "introduction",
        "passage"
      ],
      "related_entities": []
    }
  ],
  "sponsorships": [
    {
      "name": "Cromer",
      "classification": "primary",
      "entity_type": "person",
      "primary": true,
      "person_id": "~{\"chamber\": \"upper\", \"name\": \"Cromer\"}",
      "organization_id": null
    }
  ],
  "related_bills": [],
  "versions": [
    {
      "note": "05/06/2025",
      "links": [
        {
          "url": "https://www.scstatehouse.gov/sess126_2025-2026/prever/643_20250506.htm",
          "media_type": "text/html"
        }
      ],
      "date": "",
      "classification": ""
    },
    {
      "note": "Filed",
      "links": [
        {
          "url": "https://www.scstatehouse.gov/sess126_2025-2026/bills/643.htm",
          "media_type": "text/html"
        },
        {
          "url": "https://www.scstatehouse.gov/sess126_2025-2026/bills/643.docx",
          "media_type": "application/vnd.openxmlformats-officedocument.wordprocessingml.document"
        }
      ],
      "date": "",
      "classification": ""
    }
  ],
  "documents": [],
  "citations": [],
  "sources": [
    {
      "url": "https://www.scstatehouse.gov/billsearch.php?billnumbers=643&session=126&summary=B",
      "note": ""
    }
  ],
  "extras": {},
  "jurisdiction": {
    "id": "ocd-jurisdiction/country:us/state:sc/government",
    "name": "South Carolina",
    "classification": "state",
    "division_id": "ocd-division/country:us/state:sc"
  },
  "scraped_at": "2025-07-28T18:25:14+00:00",
  "_id": "342871e4-6be0-11f0-bf34-96e81bacb000"
}