{
  "legislative_session": "2025-2026",
  "identifier": "H 4151",
  "title": "Juveniles",
  "from_organization": "~{\"classification\": \"lower\"}",
  "classification": [
    "bill"
  ],
  "subject": [],
  "abstracts": [
    {
      "note": "description",
      "abstract": "A BILL TO AMEND THE SOUTH CAROLINA CODE OF LAWS BY AMENDING SECTION 63-19-20, RELATING TO TERMS DEFINED IN THE \"JUVENILE JUSTICE CODE,\" SO AS TO CHANGE THE DEFINITION OF \"CHILD\" OR \"JUVENILE,\" TO PROVIDE EXCEPTIONS FOR MINORS WHO COMMIT CERTAIN VIOLENT CRIMES, AND FOR OTHER PURPOSES."
    }
  ],
  "other_titles": [],
  "other_identifiers": [],
  "actions": [
    {
      "description": "Introduced and read first time",
      "date": "2025-03-05",
      "organization_id": "~{\"classification\": \"lower\"}",
      "classification": [
        "introduction",
        "reading-1"
      ],
      "related_entities": []
    },
    {
      "description": "Referred to Committee on Judiciary",
      "date": "2025-03-05",
      "organization_id": "~{\"classification\": \"lower\"}",
      "classification": [
        "referral-committee"
      ],
      "related_entities": []
    }
  ],
  "sponsorships": [
    {
      "name": "W. Newton",
      "classification": "primary",
      "entity_type": "person",
      "primary": true,
      "person_id": "~{\"chamber\": \"lower\", \"name\": \"W. Newton\"}",
      "organization_id": null
    },
    {
      "name": "G.M. Smith",
      "classification": "primary",
      "entity_type": "person",
      "primary": true,
      "person_id": "~{\"chamber\": \"lower\", \"name\": \"G.M. Smith\"}",
      "organization_id": null
    },
    {
      "name": "Hiott",
      "classification": "primary",
      "entity_type": "person",
      "primary": true,
      "person_id": "~{\"chamber\": \"lower\", \"name\": \"Hiott\"}",
      "organization_id": null
    },
    {
      "name": "Hixon",
      "classification": "primary",
      "entity_type": "person",
      "primary": true,
      "person_id": "~{\"chamber\": \"lower\", \"name\": \"Hixon\"}",
      "organization_id": null
    },
    {
      "name": "Caskey",
      "classification": "primary",
      "entity_type": "person",
      "primary": true,
      "person_id": "~{\"chamber\": \"lower\", \"name\": \"Caskey\"}",
      "organization_id": null
    },
    {
      "name": "Robbins",
      "classification": "primary",
      "entity_type": "person",
      "primary": true,
      "person_id": "~{\"chamber\": \"lower\", \"name\": \"Robbins\"}",
      "organization_id": null
    },
    {
      "name": "Mitchell",
      "classification": "primary",
      "entity_type": "person",
      "primary": true,
      "person_id": "~{\"chamber\": \"lower\", \"name\": \"Mitchell\"}",
      "organization_id": null
    },
    {
      "name": "Pope",
      "classification": "primary",
      "entity_type": "person",
      "primary": true,
      "person_id": "~{\"chamber\": \"lower\", \"name\": \"Pope\"}",
      "organization_id": null
    },
    {
      "name": "Gagnon",
      "classification": "primary",
      "entity_type": "person",
      "primary": true,
      "person_id": "~{\"chamber\": \"lower\", \"name\": \"Gagnon\"}",
      "organization_id": null
    },
    {
      "name": "Taylor",
      "classification": "primary",
      "entity_type": "person",
      "primary": true,
      "person_id": "~{\"chamber\": \"lower\", \"name\": \"Taylor\"}",
      "organization_id": null
    },
    {
      "name": "Whitmire",
      "classification": "primary",
      "entity_type": "person",
      "primary": true,
      "person_id": "~{\"chamber\": \"lower\", \"name\": \"Whitmire\"}",
      "organization_id": null
    },
    {
      "name": "B. Newton",
      "classification": "primary",
      "entity_type": "person",
      "primary": true,
      "person_id": "~{\"chamber\": \"lower\", \"name\": \"B. Newton\"}",
      "organization_id": null
    },
    {
      "name": "Vaughan",
      "classification": "primary",
      "entity_type": "person",
      "primary": true,
      "person_id": "~{\"chamber\": \"lower\", \"name\": \"Vaughan\"}",
      "organization_id": null
    },
    {
      "name": "Chapman",
      "classification": "primary",
      "entity_type": "person",
      "primary": true,
      "person_id": "~{\"chamber\": \"lower\", \"name\": \"Chapman\"}",
      "organization_id": null
    },
    {
      "name": "M.M. Smith",
      "classification": "primary",
      "entity_type": "person",
      "primary": true,
      "person_id": "~{\"chamber\": \"lower\", \"name\": \"M.M. Smith\"}",
      "organization_id": null
    },
    {
      "name": "J.E. Johnson",
      "classification": "primary",
      "entity_type": "person",
      "primary": true,
      "person_id": "~{\"chamber\": \"lower\", \"name\": \"J.E. Johnson\"}",
      "organization_id": null
    },
    {
      "name": "Yow",
      "classification": "primary",
      "entity_type": "person",
      "primary": true,
      "person_id": "~{\"chamber\": \"lower\", \"name\": \"Yow\"}",
      "organization_id": null
    },
    {
      "name": "Bustos",
      "classification": "primary",
      "entity_type": "person",
      "primary": true,
      "person_id": "~{\"chamber\": \"lower\", \"name\": \"Bustos\"}",
      "organization_id": null
    },
    {
      "name": "Landing",
      "classification": "primary",
      "entity_type": "person",
      "primary": true,
      "person_id": "~{\"chamber\": \"lower\", \"name\": \"Landing\"}",
      "organization_id": null
    },
    {
      "name": "Gibson",
      "classification": "primary",
      "entity_type": "person",
      "primary": true,
      "person_id": "~{\"chamber\": \"lower\", \"name\": \"Gibson\"}",
      "organization_id": null
    },
    {
      "name": "McCravy",
      "classification": "primary",
      "entity_type": "person",
      "primary": true,
      "person_id": "~{\"chamber\": \"lower\", \"name\": \"McCravy\"}",
      "organization_id": null
    },
    {
      "name": "Gilliam",
      "classification": "primary",
      "entity_type": "person",
      "primary": true,
      "person_id": "~{\"chamber\": \"lower\", \"name\": \"Gilliam\"}",
      "organization_id": null
    },
    {
      "name": "Hager",
      "classification": "primary",
      "entity_type": "person",
      "primary": true,
      "person_id": "~{\"chamber\": \"lower\", \"name\": \"Hager\"}",
      "organization_id": null
    },
    {
      "name": "Rankin",
      "classification": "primary",
      "entity_type": "person",
      "primary": true,
      "person_id": "~{\"chamber\": \"lower\", \"name\": \"Rankin\"}",
      "organization_id": null
    },
    {
      "name": "Schuessler",
      "classification": "primary",
      "entity_type": "person",
      "primary": true,
      "person_id": "~{\"chamber\": \"lower\", \"name\": \"Schuessler\"}",
      "organization_id": null
    },
    {
      "name": "Teeple",
      "classification": "primary",
      "entity_type": "person",
      "primary": true,
      "person_id": "~{\"chamber\": \"lower\", \"name\": \"Teeple\"}",
      "organization_id": null
    },
    {
      "name": "Erickson",
      "classification": "primary",
      "entity_type": "person",
      "primary": true,
      "person_id": "~{\"chamber\": \"lower\", \"name\": \"Erickson\"}",
      "organization_id": null
    },
    {
      "name": "Herbkersman",
      "classification": "primary",
      "entity_type": "person",
      "primary": true,
      "person_id": "~{\"chamber\": \"lower\", \"name\": \"Herbkersman\"}",
      "organization_id": null
    },
    {
      "name": "Hartnett",
      "classification": "primary",
      "entity_type": "person",
      "primary": true,
      "person_id": "~{\"chamber\": \"lower\", \"name\": \"Hartnett\"}",
      "organization_id": null
    },
    {
      "name": "Wooten",
      "classification": "primary",
      "entity_type": "person",
      "primary": true,
      "person_id": "~{\"chamber\": \"lower\", \"name\": \"Wooten\"}",
      "organization_id": null
    },
    {
      "name": "Lawson",
      "classification": "primary",
      "entity_type": "person",
      "primary": true,
      "person_id": "~{\"chamber\": \"lower\", \"name\": \"Lawson\"}",
      "organization_id": null
    },
    {
      "name": "Long",
      "classification": "primary",
      "entity_type": "person",
      "primary": true,
      "person_id": "~{\"chamber\": \"lower\", \"name\": \"Long\"}",
      "organization_id": null
    },
    {
      "name": "Lowe",
      "classification": "primary",
      "entity_type": "person",
      "primary": true,
      "person_id": "~{\"chamber\": \"lower\", \"name\": \"Lowe\"}",
      "organization_id": null
    }
  ],
  "related_bills": [],
  "versions": [
    {
      "note": "03/05/2025",
      "links": [
        {
          "url": "https://www.scstatehouse.gov/sess126_2025-2026/prever/4151_20250305.htm",
          "media_type": "text/html"
        }
      ],
      "date": "",
      "classification": ""
    },
    {
      "note": "Filed",
      "links": [
        {
          "url": "https://www.scstatehouse.gov/sess126_2025-2026/bills/4151.htm",
          "media_type": "text/html"
        },
        {
          "url": "https://www.scstatehouse.gov/sess126_2025-2026/bills/4151.docx",
          "media_type": "application/vnd.openxmlformats-officedocument.wordprocessingml.document"
        }
      ],
      "date": "",
      "classification": ""
    }
  ],
  "documents": [],
  "citations": [],
  "sources": [
    {
      "url": "https://www.scstatehouse.gov/billsearch.php?billnumbers=4151&session=126&summary=B",
      "note": ""
    }
  ],
  "extras": {},
  "jurisdiction": {
    "id": "ocd-jurisdiction/country:us/state:sc/government",
    "name": "South Carolina",
    "classification": "state",
    "division_id": "ocd-division/country:us/state:sc"
  },
  "scraped_at": "2025-07-28T18:32:05+00:00",
  "_id": "299191c4-6be1-11f0-bf34-96e81bacb000"
}