{
  "legislative_session": "2025-2026",
  "identifier": "H 3791",
  "title": "Property and casualty insurance",
  "from_organization": "~{\"classification\": \"lower\"}",
  "classification": [
    "concurrent resolution"
  ],
  "subject": [],
  "abstracts": [
    {
      "note": "description",
      "abstract": "A CONCURRENT RESOLUTION TO REQUEST THE UNITED STATES CONGRESS ADDRESS THE CRITICAL ISSUES FACING PROPERTY AND CASUALTY INSURANCE MARKETS ACROSS THE NATION."
    }
  ],
  "other_titles": [],
  "other_identifiers": [],
  "actions": [
    {
      "description": "Introduced",
      "date": "2025-01-28",
      "organization_id": "~{\"classification\": \"lower\"}",
      "classification": [
        "introduction"
      ],
      "related_entities": []
    },
    {
      "description": "Referred to Committee on Invitations and Memorial Resolutions",
      "date": "2025-01-28",
      "organization_id": "~{\"classification\": \"lower\"}",
      "classification": [
        "referral-committee"
      ],
      "related_entities": []
    }
  ],
  "sponsorships": [
    {
      "name": "Bailey",
      "classification": "primary",
      "entity_type": "person",
      "primary": true,
      "person_id": "~{\"chamber\": \"lower\", \"name\": \"Bailey\"}",
      "organization_id": null
    },
    {
      "name": "Hardee",
      "classification": "primary",
      "entity_type": "person",
      "primary": true,
      "person_id": "~{\"chamber\": \"lower\", \"name\": \"Hardee\"}",
      "organization_id": null
    },
    {
      "name": "McGinnis",
      "classification": "primary",
      "entity_type": "person",
      "primary": true,
      "person_id": "~{\"chamber\": \"lower\", \"name\": \"McGinnis\"}",
      "organization_id": null
    },
    {
      "name": "Hayes",
      "classification": "primary",
      "entity_type": "person",
      "primary": true,
      "person_id": "~{\"chamber\": \"lower\", \"name\": \"Hayes\"}",
      "organization_id": null
    }
  ],
  "related_bills": [],
  "versions": [
    {
      "note": "01/28/2025",
      "links": [
        {
          "url": "https://www.scstatehouse.gov/sess126_2025-2026/prever/3791_20250128.htm",
          "media_type": "text/html"
        }
      ],
      "date": "",
      "classification": ""
    },
    {
      "note": "Filed",
      "links": [
        {
          "url": "https://www.scstatehouse.gov/sess126_2025-2026/bills/3791.htm",
          "media_type": "text/html"
        },
        {
          "url": "https://www.scstatehouse.gov/sess126_2025-2026/bills/3791.docx",
          "media_type": "application/vnd.openxmlformats-officedocument.wordprocessingml.document"
        }
      ],
      "date": "",
      "classification": ""
    }
  ],
  "documents": [],
  "citations": [],
  "sources": [
    {
      "url": "https://www.scstatehouse.gov/billsearch.php?billnumbers=3791&session=126&summary=B",
      "note": ""
    }
  ],
  "extras": {},
  "jurisdiction": {
    "id": "ocd-jurisdiction/country:us/state:sc/government",
    "name": "South Carolina",
    "classification": "state",
    "division_id": "ocd-division/country:us/state:sc"
  },
  "scraped_at": "2025-07-28T18:34:58+00:00",
  "_id": "9062cecc-6be1-11f0-bf34-96e81bacb000"
}