{
  "legislative_session": "2025-2026",
  "identifier": "S 656",
  "title": "Public Utility Property",
  "from_organization": "~{\"classification\": \"upper\"}",
  "classification": [
    "bill"
  ],
  "subject": [],
  "abstracts": [
    {
      "note": "description",
      "abstract": "A BILL TO AMEND THE SOUTH CAROLINA CODE OF LAWS BY ADDING SECTION 58-5-70 SO AS TO REQUIRE THE PUBLIC SERVICE COMMISSION TO MAKE CERTAIN CONSIDERATIONS WHEN EVALUATING AN APPLICATION FOR A PUBLIC UTILITY TO ACQUIRE PROPERTY OR ASSETS USED TO PROVIDE WATER, SEWERAGE COLLECTION, OR SEWERAGE DISPOSAL OWNED BY A COUNTY, MUNICIPALITY, OR SPECIAL PURPOSE DISTRICT."
    }
  ],
  "other_titles": [],
  "other_identifiers": [],
  "actions": [
    {
      "description": "Introduced and read first time",
      "date": "2025-05-06",
      "organization_id": "~{\"classification\": \"upper\"}",
      "classification": [
        "introduction",
        "reading-1"
      ],
      "related_entities": []
    },
    {
      "description": "Referred to Committee on Judiciary",
      "date": "2025-05-06",
      "organization_id": "~{\"classification\": \"upper\"}",
      "classification": [
        "referral-committee"
      ],
      "related_entities": []
    }
  ],
  "sponsorships": [
    {
      "name": "Johnson",
      "classification": "primary",
      "entity_type": "person",
      "primary": true,
      "person_id": "~{\"chamber\": \"upper\", \"name\": \"Johnson\"}",
      "organization_id": null
    }
  ],
  "related_bills": [],
  "versions": [
    {
      "note": "05/06/2025",
      "links": [
        {
          "url": "https://www.scstatehouse.gov/sess126_2025-2026/prever/656_20250506.htm",
          "media_type": "text/html"
        }
      ],
      "date": "",
      "classification": ""
    },
    {
      "note": "Filed",
      "links": [
        {
          "url": "https://www.scstatehouse.gov/sess126_2025-2026/bills/656.htm",
          "media_type": "text/html"
        },
        {
          "url": "https://www.scstatehouse.gov/sess126_2025-2026/bills/656.docx",
          "media_type": "application/vnd.openxmlformats-officedocument.wordprocessingml.document"
        }
      ],
      "date": "",
      "classification": ""
    }
  ],
  "documents": [],
  "citations": [],
  "sources": [
    {
      "url": "https://www.scstatehouse.gov/billsearch.php?billnumbers=656&session=126&summary=B",
      "note": ""
    }
  ],
  "extras": {},
  "jurisdiction": {
    "id": "ocd-jurisdiction/country:us/state:sc/government",
    "name": "South Carolina",
    "classification": "state",
    "division_id": "ocd-division/country:us/state:sc"
  },
  "scraped_at": "2025-07-28T18:25:18+00:00",
  "_id": "36a533ee-6be0-11f0-bf34-96e81bacb000"
}